{"002256": "兆新股份", "600807": "济南高新", "002369": "卓翼科技", "002370": "亚太药业", "600322": "津投城开", "000810": "创维数字", "603398": "沐邦高科", "600577": "精达股份", "000536": "华映科技", "603122": "合富中国", "002388": "新亚制程", "002888": "惠威科技", "002771": "真视通", "000062": "深圳华强", "601020": "华钰矿业", "603215": "比依股份", "603324": "盛剑科技", "001298": "好上好", "605118": "力鼎光电", "002952": "亚世光电", "600520": "文一科技", "605136": "丽人丽妆", "600172": "黄河旋风", "002547": "春兴精工", "002652": "扬子新材", "002436": "兴森科技", "600753": "庚星股份", "002979": "雷赛智能", "001287": "中电港", "605016": "百龙创园", "600778": "友好集团", "600698": "湖南天雁", "002962": "五方光电", "600869": "远东股份", "603738": "泰晶科技", "002881": "美格智能", "000963": "华东医药", "603590": "康辰药业", "002932": "明德生物", "603160": "汇顶科技", "002642": "荣联科技", "601127": "赛力斯", "002030": "达安基因", "002819": "东方中科", "002767": "先锋电子", "601872": "招商轮船", "603488": "展鹏科技", "000908": "*ST景峰", "000819": "岳阳兴长", "002309": "*ST中利", "603056": "德邦股份", "002052": "*ST同洲", "002843": "泰嘉股份", "603065": "宿迁联盛", "600165": "*ST宁科", "600533": "栖霞建设", "605199": "葫芦娃", "000739": "普洛药业", "002189": "中光学", "605158": "华达新材", "001267": "汇绿生态", "002653": "海思科", "600050": "中国联通", "603186": "华正新材", "601799": "星宇股份", "603716": "塞力医疗", "600113": "浙江东日", "600178": "东安动力", "600216": "浙江医药", "002529": "海源复材", "002587": "奥拓电子", "002449": "国星光电", "003020": "立方制药", "600843": "上工申贝", "603639": "海利尔", "603701": "德宏股份", "603118": "共进股份", "002463": "沪电股份", "002332": "仙琚制药", "002940": "昂利康", "603387": "基蛋生物", "002130": "沃尔核材", "000158": "常山北明", "002897": "意华股份", "002022": "科华生物", "603066": "音飞储存", "605277": "新亚电子", "002094": "青岛金王", "002086": "东方海洋", "002553": "南方精工", "002301": "齐心集团", "000526": "学大教育", "603822": "嘉澳环保", "600716": "凤凰股份", "603703": "盛洋科技", "600200": "江苏吴中", "002748": "ST世龙", "600980": "北矿科技", "600463": "空港股份", "603559": "*ST通脉", "603655": "朗博科技", "000973": "佛塑科技", "002317": "众生药业", "603380": "易德龙", "002406": "远东传动", "001314": "亿道信息", "001229": "魅视科技", "002920": "德赛西威", "002037": "保利联合", "002975": "博杰股份", "000820": "神雾节能", "603993": "洛阳钼业", "600734": "实达集团", "002755": "奥赛康", "002272": "川润股份", "002055": "得润电子", "605086": "龙高股份", "002698": "博实股份", "000622": "*ST恒立", "603061": "金海通", "001259": "利仁科技", "002872": "ST天圣", "603991": "至正股份", "001359": "平安电工", "002102": "能特科技", "002655": "共达电声", "600026": "中远海能", "600418": "江淮汽车", "002199": "东晶电子", "002902": "铭普光磁", "002995": "天地在线", "002898": "赛隆药业", "603976": "正川股份", "603081": "大丰实业", "601089": "福元医药", "002957": "科瑞技术", "002855": "捷荣技术", "600926": "杭州银行", "001319": "铭科精技", "603219": "富佳股份", "000521": "长虹美菱", "603196": "日播时尚", "600868": "梅雁吉祥", "600704": "物产中大", "601128": "常熟银行", "601658": "邮储银行", "000034": "神州数码", "002738": "中矿资源", "601939": "建设银行", "002194": "武汉凡谷", "603630": "拉芳家化", "002892": "科力尔", "603979": "金诚信", "002900": "哈三联", "002512": "达华智能", "603879": "ST永悦", "605058": "澳弘电子", "600575": "淮河能源", "000933": "神火股份", "603230": "内蒙新华", "605128": "上海沿浦", "002742": "ST三圣", "000988": "华工科技", "600962": "国投中鲁", "603963": "*ST大药", "600898": "*ST美讯", "002983": "芯瑞达", "603280": "南方路机", "002817": "黄山胶囊", "600246": "万通发展", "601838": "成都银行", "002203": "海亮股份", "601133": "柏诚股份", "002923": "润都股份", "603933": "睿能科技", "002972": "科安达", "605588": "冠石科技", "600455": "博通股份", "603773": "沃格光电", "603108": "润达医疗", "601138": "工业富联", "000851": "ST高鸿", "002885": "京泉华", "600301": "华锡有色", "605116": "奥锐特", "600721": "百花医药", "603920": "世运电路", "603392": "万泰生物", "601107": "四川成渝", "601899": "紫金矿业", "600707": "彩虹股份", "600576": "祥源文旅", "002966": "苏州银行", "603722": "阿科力", "003031": "中瓷电子", "603997": "继峰股份", "601225": "陕西煤业", "002422": "科伦药业", "600938": "中国海油", "603336": "宏辉果蔬", "003015": "日久光电", "600557": "康缘药业", "002168": "惠程科技", "002632": "道明光学", "603700": "宁水集团", "605369": "拱东医疗", "002916": "深南电路", "600129": "太极集团", "601001": "晋控煤业", "601328": "交通银行", "601288": "农业银行", "601009": "南京银行", "002119": "康强电子", "603998": "方盛制药", "603439": "贵州三力", "603615": "茶花股份", "601857": "中国石油", "002876": "三利谱", "601163": "三角轮胎", "002432": "九安医疗", "603890": "春秋电子", "002556": "辉隆股份", "002036": "联创电子", "603600": "永艺股份", "002579": "中京电子", "600764": "中国海防", "000045": "深纺织Ａ", "601229": "上海银行", "002384": "东山精密", "603220": "中贝通信", "600375": "*ST汉马", "002725": "跃岭股份", "002773": "康弘药业", "002981": "朝阳科技", "601628": "中国人寿", "600908": "无锡银行", "001318": "阳光乳业", "002594": "比亚迪", "600511": "国药股份", "002636": "金安国纪", "603520": "司太立", "002948": "青岛银行", "001328": "登康口腔", "600664": "哈药股份", "603130": "云中马", "603067": "振华股份", "601919": "中远海控", "603922": "金鸿顺", "603496": "恒为科技", "600568": "ST中珠", "002938": "鹏鼎控股", "603558": "健盛集团", "600211": "西藏药业", "603277": "银都股份", "601398": "工商银行", "600071": "凤凰光学", "002457": "青龙管业", "603206": "嘉环科技", "601101": "昊华能源", "600513": "联环药业", "001367": "海森药业", "600482": "中国动力", "002155": "湖南黄金", "002038": "双鹭药业", "002510": "天汽模", "001309": "德明利", "001389": "广合科技", "002880": "卫光生物", "002082": "万邦德", "002950": "奥美医疗", "002104": "恒宝股份", "002955": "鸿合科技", "600488": "津药药业", "002584": "西陇科学", "603538": "美诺华", "600605": "汇通能源", "605398": "DR新炬网", "601975": "招商南油", "002396": "星网锐捷", "002281": "光迅科技", "601665": "齐鲁银行", "002298": "中电兴发", "600060": "海信视像", "000823": "超声电子", "601988": "中国银行", "600998": "九州通", "600000": "浦发银行", "601818": "光大银行", "002107": "沃华医药", "003021": "兆威机电", "601998": "中信银行", "000980": "众泰汽车", "601778": "晶科科技", "601825": "沪农商行", "601098": "中南传媒", "000651": "格力电器", "600661": "昂立教育", "600660": "福耀玻璃", "000566": "海南海药", "600999": "招商证券", "000333": "美的集团", "600036": "招商银行", "601577": "长沙银行", "601728": "中国电信", "002835": "同为股份", "002562": "兄弟科技", "002588": "史丹利", "603319": "湘油泵", "001308": "康冠科技", "600256": "广汇能源", "002660": "茂硕电源", "603699": "纽威股份", "000889": "ST中嘉", "002251": "*ST步高", "002785": "万里石", "603042": "华脉科技", "002847": "盐津铺子", "000790": "华神科技", "601898": "中煤能源", "603138": "海量数据", "603987": "康德莱", "600182": "S佳通", "600777": "ST新潮", "002382": "蓝帆医疗", "002289": "ST宇顺", "601169": "北京银行", "002845": "同兴达", "603323": "苏农银行", "600222": "太龙药业", "603348": "文灿股份", "603023": "*ST威帝", "600601": "方正科技", "002058": "威尔泰", "003019": "宸展光电", "601319": "中国人保", "603260": "合盛硅业", "000788": "北大医药", "002213": "大为股份", "601916": "浙商银行", "603929": "亚翔集成", "603676": "卫信康", "601600": "中国铝业", "000532": "华金资本", "603209": "兴通股份", "600522": "中天科技", "603121": "华培动力", "603193": "润本股份", "600346": "恒力石化", "000766": "通化金马", "002947": "恒铭达", "600288": "大恒科技", "002437": "誉衡药业", "603172": "万丰股份", "600020": "中原高速", "002001": "新 和 成", "603283": "赛腾股份", "002045": "国光电器", "000909": "ST数源", "002351": "漫步者", "002997": "瑞鹄模具", "000628": "高新发展", "002527": "新时达", "003028": "振邦智能", "600548": "深高速", "603386": "骏亚科技", "000727": "冠捷科技", "002617": "露笑科技", "603685": "晨丰科技", "000001": "平安银行", "603328": "依顿电子", "600226": "亨通股份", "002150": "通润装备", "002032": "苏 泊 尔", "600018": "上港集团", "600015": "华夏银行", "603605": "珀莱雅", "002976": "瑞玛精密", "001208": "华菱线缆", "600566": "济川药业", "600928": "西安银行", "002012": "凯恩股份", "600331": "宏达股份", "603198": "迎驾贡酒", "001278": "一彬科技", "001238": "浙江正特", "002475": "立讯精密", "601668": "中国建筑", "002444": "巨星科技", "605186": "健麾信息", "603917": "合力科技", "603286": "日盈电子", "603585": "苏利股份", "002841": "视源股份", "600360": "ST华微", "601607": "上海医药", "601298": "青岛港", "002689": "远大智能", "002416": "爱施德", "605507": "国邦医药", "002134": "天津普林", "002589": "瑞康医药", "001231": "农心科技", "605499": "东鹏饮料", "601088": "中国神华", "002609": "捷顺科技", "603507": "振江股份", "002993": "奥海科技", "001373": "翔腾新材", "600272": "开开实业", "605005": "合兴股份", "000656": "*ST金科", "601601": "中国太保", "600789": "鲁抗医药", "002020": "京新药业", "601166": "兴业银行", "000833": "粤桂股份", "002958": "青农商行", "002626": "金达威", "000888": "峨眉山Ａ", "601168": "西部矿业", "002633": "申科股份", "601801": "皖新传媒", "605555": "德昌股份", "002352": "顺丰控股", "600888": "新疆众和", "002648": "卫星化学", "002793": "罗欣药业", "600362": "江西铜业", "000547": "航天发展", "002139": "拓邦股份", "002877": "智能自控", "603718": "海利生物", "603158": "腾龙股份", "600821": "金开新能", "600976": "健民集团", "600426": "华鲁恒升", "601021": "春秋航空", "603199": "九华旅游", "002004": "华邦健康", "600839": "四川长虹", "002796": "世嘉科技", "601318": "中国平安", "600167": "联美控股", "002637": "赞宇科技", "603222": "济民健康", "002980": "华盛昌", "600010": "包钢股份", "002261": "拓维信息", "600035": "楚天高速", "603087": "甘李药业", "600056": "中国医药", "002093": "国脉科技", "002371": "北方华创", "603229": "奥翔药业", "002736": "国信证券", "002799": "环球印务", "002106": "莱宝高科", "603341": "龙旗科技", "002252": "上海莱士", "003016": "欣贺股份", "002864": "盘龙药业", "002148": "北纬科技", "002990": "盛视科技", "002836": "新宏泽", "001380": "华纬科技", "601019": "山东出版", "003011": "海象新材", "603002": "宏昌电子", "002209": "达 意 隆", "002779": "中坚科技", "001225": "和泰机电", "600521": "华海药业", "002564": "*ST天沃", "603189": "网达软件", "603629": "利通电子", "002566": "益盛药业", "000915": "华特达因", "600594": "益佰制药", "600233": "圆通速递", "002599": "盛通股份", "003007": "直真科技", "000999": "华润三九", "600130": "波导股份", "002248": "华东数控", "605258": "协和电子", "601997": "贵阳银行", "601187": "厦门银行", "605365": "立达信", "600016": "民生银行", "605066": "天正电气", "603211": "晋拓股份", "601963": "重庆银行", "000408": "藏格矿业", "002650": "ST加加", "603088": "宁波精达", "600103": "青山纸业", "600479": "千金药业", "600255": "鑫科材料", "600196": "复星医药", "001206": "依依股份", "601018": "宁波港", "600329": "达仁堂", "605333": "沪光股份", "002807": "江阴银行", "002366": "融发核电", "603557": "ST起步", "002654": "万润科技", "002362": "汉王科技", "000659": "珠海中富", "002757": "南兴股份", "002907": "华森制药", "600613": "神奇制药", "002275": "桂林三金", "600803": "新奥股份", "603085": "天成自控", "000020": "深华发Ａ", "000756": "新华制药", "603656": "泰禾智能", "600105": "永鼎股份", "600309": "万华化学", "600817": "宇通重工", "600997": "开滦股份", "600420": "国药现代", "605580": "恒盛能源", "002313": "日海智能", "002231": "奥维通信", "605255": "天普股份", "600188": "兖矿能源", "600080": "金花股份", "603239": "浙江仙通", "002896": "中大力德", "601928": "凤凰传媒", "600332": "白云山", "600276": "恒瑞医药", "002474": "榕基软件", "002595": "豪迈科技", "000425": "徐工机械", "600422": "昆药集团", "600690": "XD海尔智", "002273": "水晶光电", "603696": "安记食品", "001227": "兰州银行", "601956": "东贝集团", "603096": "新经典", "603360": "百傲化学", "000166": "申万宏源", "003010": "若羽臣", "000426": "兴业银锡", "000893": "亚钾国际", "002901": "大博医疗", "000695": "滨海能源", "601866": "中远海发", "603633": "徕木股份", "002009": "天奇股份", "002365": "永安药业", "603660": "苏州科达", "601860": "紫金银行", "002551": "尚荣医疗", "600267": "海正药业", "000952": "广济药业", "601162": "天风证券", "601077": "渝农商行", "605376": "博迁新材", "605298": "必得科技", "000625": "长安汽车", "003006": "百亚股份", "605366": "宏柏新材", "600801": "华新水泥", "605389": "长龄液压", "002635": "安洁科技", "002376": "新北洋", "000698": "沈阳化工", "000153": "丰原药业", "002315": "焦点科技", "000818": "航锦科技", "002873": "新天药业", "000676": "智度股份", "002866": "传艺科技", "000960": "锡业股份", "002412": "汉森制药", "001306": "夏厦精密", "002440": "闰土股份", "002662": "京威股份", "002287": "奇正藏药", "603356": "华菱精工", "000571": "新大洲A", "002485": "ST雪发", "601336": "新华保险", "601390": "中国中铁", "000159": "国际实业", "002014": "永新股份", "600476": "湘邮科技", "000692": "惠天热电", "002415": "海康威视", "000703": "恒逸石化", "603082": "北自科技", "601058": "赛轮轮胎", "000156": "华数传媒", "603860": "中公高科", "003025": "思进智能", "603811": "诚意药业", "002197": "ST证通", "603112": "华翔股份", "600519": "贵州茅台", "603579": "荣泰健康", "000919": "金陵药业", "002467": "二六三", "002399": "海普瑞", "002600": "领益智造", "603015": "弘讯科技", "600983": "惠而浦", "002349": "精华制药", "002644": "佛慈制药", "002988": "豪美新材", "600536": "中国软件", "002559": "亚威股份", "603355": "莱克电气", "600033": "福建高速", "603535": "嘉诚国际", "002516": "旷达科技", "600115": "中国东航", "000725": "京东方Ａ", "603079": "圣达生物", "600919": "江苏银行", "603163": "圣晖集成", "603266": "天龙股份", "603508": "思维列控", "002583": "海能达", "603606": "东方电缆", "000931": "中 关 村", "603351": "威尔药业", "002244": "滨江集团", "600986": "浙文互联", "603908": "牧高笛", "003032": "传智教育", "002515": "金字火腿", "000596": "古井贡酒", "601918": "新集能源", "000063": "中兴通讯", "002937": "兴瑞科技", "601633": "长城汽车", "603259": "药明康德", "002065": "东华软件", "600713": "南京医药", "601339": "百隆东方", "605368": "蓝天燃气", "601598": "中国外运", "601968": "宝钢包装", "002236": "大华股份", "002752": "N兴股份", "002627": "三峡旅游", "001387": "雪祺电气", "603931": "格林达", "002765": "蓝黛科技", "603228": "景旺电子", "002137": "实益达", "600925": "苏能股份", "605001": "威奥股份", "603986": "兆易创新", "002290": "禾盛新材", "600645": "中源协和", "002294": "信立泰", "002943": "宇晶股份", "603236": "移远通信", "600085": "同仁堂", "002675": "东诚药业", "002387": "维信诺", "002016": "世荣兆业", "601007": "金陵饭店", "603613": "国联股份", "600229": "城市传媒", "601061": "中信金属", "600377": "宁沪高速", "002532": "天山铝业", "002117": "东港股份", "000050": "深天马Ａ", "000815": "美利云", "002222": "福晶科技", "601811": "新华文轩", "603809": "豪能股份", "000544": "中原环保", "600750": "江中药业", "603019": "中科曙光", "002745": "木林森", "002889": "东方嘉盛", "002017": "东信和平", "600123": "兰花科创", "600757": "长江传媒", "002815": "崇达技术", "000555": "神州信息", "603368": "柳药集团", "603311": "金海高科", "000737": "北方铜业", "601921": "浙版传媒", "600081": "东风科技", "600338": "西藏珠峰", "002987": "京北方", "603690": "至纯科技", "600756": "浪潮软件", "603156": "养元饮品", "002810": "山东赫达", "603225": "新凤鸣", "002925": "盈趣科技", "605259": "绿田机械", "601688": "XD华泰证", "603255": "鼎际得", "002956": "西麦食品", "000021": "深科技", "603039": "泛微网络", "002395": "双象股份", "600535": "天士力", "603882": "金域医学", "601699": "潞安环能", "002971": "和远气体", "002912": "中新赛克", "603095": "越剑智能", "603895": "天永智能", "000858": "五 粮 液", "002737": "葵花药业", "603322": "超讯通信", "600161": "天坛生物", "603996": "退市中新", "603959": "ST百利", "603880": "南卫股份", "603855": "华荣股份", "603829": "洛凯股份", "603619": "中曼石油", "603603": "退市博天", "603555": "ST贵人", "603361": "浙江国祥", "603358": "华达科技", "603313": "梦百合", "603301": "振德医疗", "603276": "恒兴新材", "603256": "宏和科技", "603207": "小方制药", "603159": "上海亚虹", "603157": "退市拉夏", "603133": "退市碳元", "603089": "正裕工业", "603083": "剑桥科技", "603070": "万控智造", "603025": "大豪科技", "603016": "新宏泰", "601989": "中国重工", "601766": "中国中车", "601558": "退市锐电", "601528": "瑞丰银行", "601518": "吉林高速", "601366": "利群股份", "601299": "中国北车", "601268": "*ST二重", "601258": "*ST庞大", "601231": "环旭电子", "601186": "中国铁建", "601118": "海南橡胶", "601111": "中国国航", "600991": "广汽长丰", "600978": "*ST宜生", "600899": "*ST信联", "600896": "退市海医", "600892": "大晟文化", "600891": "退市秋林", "600890": "退市中房", "600886": "国投电力", "600878": "*ST北科", "600870": "退市厦华", "600856": "退市中天", "600852": "*ST中川", "600849": "上药转换", "600842": "中西药业", "600840": "新湖创业", "600836": "*ST易连", "600832": "东方明珠", "600823": "*ST世茂", "600815": "厦工股份", "600813": "ST鞍一工", "600812": "华北制药", "600811": "东方集团", "600806": "退市昆机", "600799": "*ST龙科", "600788": "*ST达曼", "600786": "东方锅炉", "600784": "鲁银投资", "600781": "退市辅仁", "600776": "东方通信", "600772": "S*ST龙昌", "600767": "退市运盛", "600766": "退市园城", "600762": "S*ST金荔", "600752": "*ST哈慈", "600751": "海航科技", "600747": "退市大控", "600746": "江苏索普", "600723": "首商股份", "600709": "ST生态", "600701": "退市工新", "600700": "*ST数码", "600695": "退市绿庭", "600687": "退市刚泰", "600680": "*ST上普", "600677": "*ST航通", "600672": "*ST华圣", "600670": "*ST斯达", "600669": "*ST鞍成", "600659": "*ST花雕", "600656": "退市博元", "600652": "退市游久", "600647": "退市同达", "600646": "ST国嘉", "600634": "退市富控", "600632": "华联商厦", "600631": "百联股份", "600627": "上电股份", "600625": "PT水仙", "600614": "退市鹏起", "600607": "上实医药", "600602": "云赛智联", "600592": "龙溪股份", "600591": "*ST上航", "600572": "康恩贝", "600565": "ST迪马", "600555": "退市海创", "600553": "太行水泥", "600551": "时代出版", "600549": "厦门钨业", "600532": "退市未来", "600485": "*ST信威", "600472": "包头铝业", "600466": "*ST蓝光", "600432": "退市吉恩", "600401": "退市海润", "600393": "ST粤泰", "600385": "退市金泰", "600357": "承德钒钛", "600326": "西藏天路", "600321": "正源股份", "600317": "营口港", "600311": "*ST荣华", "600307": "酒钢宏兴", "600306": "退市商城", "600303": "ST曙光", "600297": "广汇汽车", "600296": "S兰铝", "600291": "退市西水", "600290": "*ST华仪", "600286": "S*ST国瓷", "600277": "ST亿利", "600275": "退市昌鱼", "600270": "外运发展", "600263": "路桥建设", "600261": "阳光照明", "600260": "*ST凯乐", "600253": "天方药业", "600251": "冠农股份", "600247": "*ST成城", "600243": "青海华鼎", "600242": "退市中昌", "600240": "退市华业", "600237": "铜峰电子", "600220": "ST阳光", "600219": "南山铝业", "600213": "*ST亚星", "600209": "退市罗顿", "600205": "S山东铝", "600193": "创兴资源", "600181": "S*ST云大", "600175": "退市美都", "600146": "退市环球", "600145": "退市新亿", "600139": "*ST西源", "600122": "*ST宏图", "600112": "*ST天成", "600102": "莱钢股份", "600093": "退市易见", "600092": "S*ST精密", "600091": "退市明科", "600090": "退市济堂", "600087": "退市长油", "600086": "退市金钰", "600077": "*ST宋都", "600074": "退市保千", "600069": "退市银鸽", "600068": "葛洲坝", "600065": "*ST联谊", "600051": "宁波联合", "600005": "武钢股份", "600003": "ST东北高", "600002": "齐鲁石化", "600001": "邯郸钢铁", "003816": "中国广核", "003036": "泰坦股份", "003005": "竞业达", "002936": "郑州银行", "002839": "张家港行", "002830": "名雕股份", "002781": "奇信退", "002776": "*ST柏龙", "002770": "科迪退", "002763": "汇洁股份", "002751": "易尚退", "002740": "*ST爱迪", "002711": "欧浦退", "002699": "*ST美盛", "002684": "猛狮退", "002681": "奋达科技", "002680": "长生退", "002665": "ST航高", "002622": "皓宸医疗", "002621": "*ST美吉", "002619": "*ST艾格", "002618": "丹邦退", "002610": "ST爱康", "002604": "龙力退", "002603": "以岭药业", "002509": "天茂退", "002505": "鹏都农牧", "002504": "*ST弘高", "002503": "*ST搜特", "002502": "ST鼎龙", "002499": "科林退", "002477": "雏鹰退", "002473": "圣莱退", "002464": "众应退", "002462": "嘉事堂", "002451": "摩恩电气", "002450": "康得退", "002447": "晨鑫退", "002441": "众业达", "002435": "ST长康", "002433": "太安退", "002426": "胜利精密", "002420": "毅昌科技", "002417": "深南退", "002411": "必康退", "002390": "信邦制药", "002359": "北讯退", "002341": "ST新纶", "002340": "格林美", "002325": "*ST洪涛", "002323": "雅博股份", "002319": "乐通股份", "002303": "美盈森", "002288": "*ST超华", "002282": "博深股份", "002280": "ST联络", "002260": "德奥退", "002220": "天宝退", "002198": "嘉应制药", "002195": "岩山科技", "002152": "广电运通", "002147": "新光退", "002143": "印纪退", "002122": "汇洲智能", "002118": "*ST紫鑫", "002113": "*ST天润", "002089": "新海退", "002087": "新纺退", "002071": "长城退", "002070": "众和退", "002018": "华信退", "002013": "中航机电", "002007": "华兰生物", "002005": "ST德豪", "002002": "ST鸿达", "000996": "中期退", "000982": "中银绒业", "000979": "中弘退", "000978": "桂林旅游", "000976": "*ST华铁", "000971": "*ST高升", "000961": "ST中南", "000956": "中原油气", "000948": "南天信息", "000939": "凯迪退", "000918": "*ST嘉凯", "000916": "华北高速", "000900": "现代投资", "000878": "云南铜业", "000866": "扬子石化", "000861": "海印股份", "000836": "ST富通", "000835": "长动退", "000832": "*ST龙涤", "000827": "*ST长兴", "000817": "辽河油田", "000806": "银河退", "000805": "*ST炎黄", "000787": "*ST创智", "000780": "ST平能", "000769": "*ST大菲", "000765": "*ST华信", "000763": "锦州石化", "000760": "斯太退", "000753": "漳州发展", "000748": "长城信息", "000732": "ST泰禾", "000730": "*ST环保", "000699": "S*ST佳纸", "000693": "华泽退", "000689": "ST宏业", "000687": "华讯退", "000675": "ST银山", "000673": "当代退", "000671": "ST阳光城", "000667": "ST美置", "000666": "经纬纺机", "000662": "天夏退", "000660": "*ST南华", "000658": "ST海洋", "000653": "ST九州", "000630": "铜陵有色", "000621": "*ST比特", "000618": "吉林化工", "000616": "*ST海投", "000613": "东海A退", "000611": "天首退", "000606": "顺利退", "000602": "金马集团", "000594": "国恒退", "000588": "PT粤金曼", "000587": "*ST金洲", "000585": "东电退", "000583": "S*ST托普", "000578": "盐湖集团", "000569": "长城股份", "000562": "宏源证券", "000556": "PT南洋", "000549": "S湘火炬", "000542": "TCL通讯", "000541": "佛山照明", "000540": "*ST中天", "000535": "*ST猴王", "000527": "美的电器", "000522": "白云山A", "000515": "攀渝钛业", "000511": "烯碳退", "000508": "琼民源A", "000502": "绿景退", "000418": "小天鹅A", "000416": "*ST民控", "000413": "ST旭电", "000412": "ST五环", "000406": "石油大明", "000405": "ST鑫光", "000150": "*ST宜康", "000047": "ST中侨", "000046": "*ST泛海", "000038": "大通退", "000033": "新都退", "000024": "招商地产", "000023": "*ST深天", "000018": "神城A退", "000015": "PT中浩A", "000013": "*ST石化A", "000008": "神州高铁", "000005": "ST星源", "000003": "PT金田A", "002991": "甘源食品", "601567": "三星医疗", "603859": "能科科技", "605319": "无锡振华", "002690": "美亚光电", "600498": "烽火通信", "002977": "天箭科技", "603826": "坤彩科技", "001256": "炜冈科技", "002879": "长缆科技", "600941": "中国移动", "600104": "XD上汽集", "603650": "彤程新材", "002967": "广电计量", "002053": "云南能投", "600380": "健康元", "603767": "中马传动", "600584": "长电科技", "603068": "博通集成", "002782": "可立克", "600873": "梅花生物", "603232": "格尔软件", "000513": "丽珠集团", "000026": "飞亚达", "001979": "招商蛇口", "603004": "鼎龙科技", "600131": "国网信通", "600867": "通化东宝", "002380": "科远智慧", "600830": "香溢融通", "600887": "伊利股份", "600996": "贵广网络", "600718": "东软集团", "603728": "鸣志电器", "002649": "博彦科技", "600031": "三一重工", "002903": "宇环数控", "600967": "内蒙一机", "603936": "博敏电子", "603127": "昭衍新药", "000752": "ST西发", "002837": "英维克", "603886": "元祖股份", "601006": "大秦铁路", "002034": "旺能环境", "603367": "辰欣药业", "002886": "沃特股份", "600028": "中国石化", "002929": "润建股份", "600598": "北大荒", "001283": "豪鹏科技", "000157": "中联重科", "002025": "航天电器", "000997": "新 大 陆", "002403": "爱仕达", "603297": "永新光学", "603970": "中农立华", "603568": "伟明环保", "605088": "冠盛股份", "600406": "国电南瑞", "603912": "佳力图", "603707": "健友股份", "001339": "智微智能", "603011": "合锻智能", "600829": "人民同泰", "600111": "北方稀土", "603878": "武进不锈", "000650": "仁和药业", "605189": "富春染织", "603677": "奇精机械", "600428": "中远海特", "000617": "中油资本", "000936": "华西股份", "002099": "海翔药业", "000682": "东方电子", "000538": "云南白药", "002378": "章源钨业", "001268": "联合精密", "603662": "柯力传感", "002849": "威星智能", "002870": "香山股份", "603150": "万朗磁塑", "601958": "金钼股份", "600191": "华资实业", "600084": "中信尼雅", "002921": "联诚精密", "603999": "读者传媒", "605378": "野马电池", "000950": "重药控股", "603956": "威派格", "603166": "福达股份", "600985": "淮北矿业", "003001": "中岩大地", "600797": "浙大网新", "600754": "锦江酒店", "002255": "海陆重工", "605589": "圣泉集团", "600731": "湖南海利", "002674": "兴业科技", "605077": "华康股份", "600089": "特变电工", "600837": "海通证券", "603102": "百合股份", "002161": "远 望 谷", "002724": "海洋王", "002697": "红旗连锁", "000070": "ST特信", "603125": "常青科技", "605289": "罗曼股份", "002184": "海得控制", "600055": "万东医疗", "002156": "通富微电", "002802": "洪汇新材", "601777": "力帆科技", "002185": "华天科技", "600968": "海油发展", "002337": "赛象科技", "600030": "中信证券", "600062": "华润双鹤", "600298": "安琪酵母", "603928": "兴业股份", "603788": "宁波高发", "600153": "建发股份", "000409": "云鼎科技", "600183": "生益科技", "002028": "思源电气", "600279": "重庆港", "601177": "杭齿前进", "600348": "华阳股份", "000028": "国药一致", "603587": "地素时尚", "600640": "国脉文化", "002409": "雅克科技", "605099": "共创草坪", "000665": "湖北广电", "600847": "万里股份", "600558": "大西洋", "002908": "德生科技", "002424": "ST百灵", "603080": "新疆火炬", "603027": "千禾味业", "600487": "亨通光电", "603551": "奥普科技", "600523": "贵航股份", "603165": "荣晟环保", "002524": "光正眼科", "002809": "红墙股份", "603373": "安邦护卫", "600995": "南网储能", "600308": "华泰股份", "002730": "电光科技", "603258": "电魂网络", "000637": "茂化实华", "603053": "成都燃气", "000403": "派林生物", "000881": "中广核技", "603238": "诺邦股份", "600425": "青松建化", "603858": "步长制药", "600794": "保税科技", "002160": "常铝股份", "603006": "联明股份", "002899": "英派斯", "000762": "西藏矿业", "600508": "上海能源", "601788": "光大证券", "603327": "福蓉科技", "600771": "广誉远", "605155": "西大门", "603803": "瑞斯康达", "601991": "大唐发电", "000807": "云铝股份", "603589": "口子窖", "002095": "生 意 宝", "002008": "大族激光", "605300": "佳禾食品", "002831": "裕同科技", "001218": "丽臣实业", "600017": "日照港", "002818": "富森美", "605599": "菜百股份", "603073": "彩蝶实业", "000937": "冀中能源", "601985": "中国核电", "002882": "金龙羽", "000517": "荣安地产", "605098": "行动教育", "000977": "浪潮信息", "603298": "杭叉集团", "601611": "中国核建", "605228": "神通科技", "000700": "模塑科技", "600048": "保利发展", "002895": "川恒股份", "601022": "宁波远洋", "603608": "*ST天创", "600379": "宝光股份", "000983": "山西焦煤", "002316": "ST亚联", "601399": "国机重装", "601377": "兴业证券", "000554": "泰山石油", "600530": "交大昂立", "002128": "电投能源", "002408": "齐翔腾达", "600497": "驰宏锌锗", "603031": "安孚科技", "000751": "锌业股份", "605567": "春雪食品", "600895": "张江高科", "002823": "凯中精密", "600177": "雅戈尔", "603856": "东宏股份", "601158": "重庆水务", "001378": "德冠新材", "002540": "亚太科技", "603416": "信捷电气", "002172": "澳洋健康", "001205": "盛航股份", "002379": "宏创控股", "600971": "恒源煤电", "001311": "多利科技", "002978": "安宁股份", "002986": "宇新股份", "000705": "浙江震元", "603201": "常润股份", "002400": "省广集团", "002064": "华峰化学", "600529": "山东药玻", "000776": "广发证券", "600759": "洲际油气", "002393": "力生制药", "002228": "合兴包装", "601211": "国泰君安", "600905": "三峡能源", "603817": "海峡环保", "603275": "众辰科技", "600423": "柳化股份", "600252": "中恒集团", "600616": "金枫酒业", "603519": "立霸股份", "600654": "中安科", "002581": "未名医药", "002401": "中远海科", "603610": "麒盛科技", "603369": "今世缘", "002421": "达实智能", "601868": "中国能建", "600373": "中文传媒", "002768": "国恩股份", "002138": "顺络电子", "603106": "恒银科技", "002530": "金财互联", "603567": "珍宝岛", "603669": "灵康药业", "002552": "宝鼎科技", "000429": "粤高速Ａ", "603578": "三星新材", "001207": "联科科技", "603203": "快克智能", "605100": "华丰股份", "002115": "三维通信", "002984": "森麒麟", "002262": "恩华药业", "000932": "华菱钢铁", "605162": "新中港", "002657": "中科金财", "600400": "红豆股份", "002703": "浙江世宝", "002721": "ST金一", "600285": "羚锐制药", "605151": "西上海", "000731": "四川美丰", "001296": "长江材料", "603009": "北特科技", "600936": "广西广电", "000911": "广农糖业", "002913": "奥士康", "603607": "京华激光", "603223": "恒通股份", "002528": "ST英飞拓", "000926": "福星股份", "603983": "丸美股份", "002592": "ST八菱", "000906": "浙商中拓", "002050": "三花智控", "000755": "山西高速", "601233": "桐昆股份", "600197": "伊力特", "001301": "尚太科技", "002687": "乔治白", "603190": "亚通精工", "603107": "上海汽配", "603379": "三美股份", "002580": "圣阳股份", "002884": "凌霄泵业", "002772": "众兴菌业", "002311": "海大集团", "600810": "神马股份", "002959": "小熊电器", "600025": "华能水电", "601717": "郑煤机", "000582": "北部湾港", "002438": "江苏神通", "003003": "天元股份", "002263": "大东南", "601066": "中信建投", "002942": "新农股份", "600328": "中盐化工", "600573": "惠泉啤酒", "003043": "华亚智能", "001260": "坤泰股份", "603289": "泰瑞机器", "000100": "TCL科技", "600582": "天地科技", "600029": "南方航空", "600871": "石化油服", "002363": "隆基机械", "002688": "金河生物", "002550": "千红制药", "600388": "龙净环保", "605338": "巴比食品", "600735": "新华锦", "600722": "金牛化工", "600150": "中国船舶", "002192": "融捷股份", "002347": "泰尔股份", "000726": "鲁  泰Ａ", "002708": "光洋股份", "000822": "山东海化", "600054": "黄山旅游", "605566": "福莱蒽特", "600004": "白云机场", "600353": "旭光电子", "003018": "金富科技", "600459": "贵研铂业", "603466": "风语筑", "603235": "天新药业", "601789": "宁波建工", "002472": "双环传动", "601360": "三六零", "002346": "柘中股份", "000048": "京基智农", "002811": "郑中设计", "603968": "醋化股份", "002098": "浔兴股份", "605399": "晨光新材", "603200": "上海洗霸", "000778": "新兴铸管", "603881": "数据港", "601686": "友发集团", "601008": "连云港", "600793": "宜宾纸业", "600503": "华丽家族", "603139": "康惠制药", "600382": "广东明珠", "002906": "华阳集团", "601199": "江南水务", "000615": "ST美谷", "603035": "常熟汽饰", "605318": "法狮龙", "600668": "尖峰集团", "600866": "星湖科技", "600198": "大唐电信", "600958": "东方证券", "002826": "易明医药", "002144": "宏达高科", "002320": "海峡股份", "603915": "国茂股份", "600981": "汇鸿集团", "002891": "中宠股份", "002612": "朗姿股份", "002178": "延华智能", "600515": "海南机场", "000711": "*ST京蓝", "605183": "确成股份", "000636": "风华高科", "000902": "新洋丰", "000564": "供销大集", "601609": "金田股份", "002917": "金奥博", "002221": "东华能源", "605008": "长鸿高科", "002821": "凯莱英", "002491": "通鼎互联", "603602": "纵横通信", "000938": "紫光股份", "600642": "申能股份", "600339": "中油工程", "000962": "东方钽业", "605122": "四方新材", "600987": "航民股份", "600292": "远达环保", "603048": "浙江黎明", "600900": "长江电力", "603556": "海兴电力", "600850": "电科数字", "001219": "青岛食品", "601099": "太平洋", "603595": "东尼电子", "002300": "太阳电缆", "000729": "燕京啤酒", "600790": "轻纺城", "002026": "山东威达", "600666": "ST瑞德", "601618": "中国中冶", "603309": "维力医疗", "603757": "大元泵业", "600903": "贵州燃气", "600673": "东阳光", "603037": "凯众股份", "002602": "世纪华通", "002519": "银河电子", "002322": "理工能科", "603500": "祥和实业", "600114": "东睦股份", "603231": "索宝蛋白", "601965": "中国汽研", "605138": "盛泰集团", "002538": "司尔特", "603779": "威龙股份", "000533": "顺钠股份", "600446": "金证股份", "603799": "华友钴业", "002546": "新联电子", "605068": "明新旭腾", "600228": "返利科技", "600271": "航天信息", "002091": "江苏国泰", "000800": "一汽解放", "600119": "长江投资", "003029": "吉大正元", "002230": "科大讯飞", "002705": "新宝股份", "002042": "华孚时尚", "000410": "沈阳机床", "603798": "康普顿", "603665": "康隆达", "601888": "中国中免", "600853": "龙建股份", "002394": "联发股份", "000985": "大庆华科", "000589": "贵州轮胎", "600775": "南京熊猫", "002279": "久其软件", "000683": "远兴能源", "001211": "双枪科技", "600356": "恒丰纸业", "600019": "宝钢股份", "002048": "宁波华翔", "603982": "泉峰汽车", "603161": "科华控股", "601877": "正泰电器", "000750": "国海证券", "603216": "梦天家居", "601113": "华鼎股份", "603167": "渤海轮渡", "600648": "外高桥", "002716": "湖南白银", "002970": "锐明技术", "600037": "歌华有线", "002825": "纳尔股份", "603896": "寿仙谷", "603169": "兰石重装", "002733": "雄韬股份", "002364": "中恒电气", "603867": "新化股份", "002391": "长青股份", "000623": "吉林敖东", "000019": "深粮控股", "002701": "奥瑞金", "600009": "上海机场", "601966": "玲珑轮胎", "002169": "智光电气", "603927": "中科软", "603325": "博隆技术", "605033": "美邦股份", "601137": "博威合金", "002461": "珠江啤酒", "603296": "华勤技术", "603331": "百达精工", "603897": "长城科技", "600352": "浙江龙盛", "000049": "德赛电池", "603060": "国检集团", "600959": "江苏有线", "600190": "ST锦港", "002683": "广东宏大", "002101": "广东鸿图", "600606": "绿地控股", "600569": "安阳钢铁", "600282": "南钢股份", "000626": "远大控股", "600685": "中船防务", "600390": "五矿资本", "002049": "紫光国微", "603261": "立航科技", "605003": "众望布艺", "601616": "广电电气", "601588": "北辰实业", "002676": "顺威股份", "002470": "金正大", "000592": "平潭发展", "002448": "中原内配", "600703": "三安光电", "601878": "浙商证券", "002162": "悦心健康", "601218": "吉鑫科技", "601121": "宝地矿业", "605055": "迎丰股份", "600833": "第一医药", "600763": "通策医疗", "603421": "鼎信通讯", "600531": "豫光金铅", "002078": "太阳纸业", "601669": "中国电建", "000557": "西部创业", "000060": "中金岭南", "600143": "金发科技", "603611": "诺力股份", "605218": "伟时电子", "603868": "飞科电器", "603601": "再升科技", "002935": "天奥电子", "002283": "天润工业", "000552": "甘肃能化", "002402": "和而泰", "600433": "冠豪高新", "002274": "华昌化工", "000869": "张  裕Ａ", "002848": "高斯贝尔", "002663": "普邦股份", "000590": "启迪药业", "000688": "国城矿业", "002235": "安妮股份", "001282": "三联锻造", "600162": "香江控股", "002846": "英联股份", "000027": "深圳能源", "603052": "可川科技", "600608": "ST沪科", "002404": "嘉欣丝绸", "002926": "华西证券", "600088": "中视传媒", "601999": "XD出版传", "600462": "*ST九有", "000848": "承德露露", "600350": "山东高速", "600585": "海螺水泥", "603661": "恒林股份", "600469": "风神股份", "002489": "浙江永强", "000523": "红棉股份", "600865": "百大集团", "603281": "江瀚新材", "603926": "铁流股份", "603022": "新通联", "600694": "大商股份", "603214": "爱婴室", "600667": "太极实业", "601212": "白银有色", "002797": "第一创业", "000831": "中国稀土", "000710": "贝瑞基因", "603320": "迪贝电气", "601003": "柳钢股份", "003040": "楚天龙", "603307": "扬州金泉", "600378": "昊华科技", "600507": "方大特钢", "601700": "风范股份", "000506": "*ST中润", "600897": "厦门空港", "000707": "双环科技", "600989": "宝丰能源", "603889": "新澳股份", "600804": "*ST鹏博", "600022": "山东钢铁", "601990": "南京证券", "600699": "均胜电子", "600273": "嘉化能源", "002029": "七 匹 狼", "600160": "巨化股份", "603638": "艾迪精密", "600410": "华胜天成", "600333": "长春燃气", "000792": "盐湖股份", "603668": "天马科技", "002727": "一心堂", "600180": "瑞茂通", "002922": "伊戈尔", "002164": "宁波东力", "600955": "维远股份", "601880": "辽港股份", "600637": "东方明珠", "600289": "*ST信通", "600249": "两面针", "603901": "永创智能", "603848": "好太太", "600728": "佳都科技", "002520": "日发精机", "000681": "视觉中国", "601800": "中国交建", "603871": "嘉友国际", "605598": "上海港湾", "002762": "金发拉比", "002186": "全 聚 德", "000581": "威孚高科", "601555": "东吴证券", "001323": "慕思股份", "603967": "中创物流", "000910": "大亚圣象", "000039": "中集集团", "600745": "闻泰科技", "600809": "山西汾酒", "600600": "青岛啤酒", "003009": "中天火箭", "600215": "派斯林", "600108": "亚盛集团", "000920": "沃顿科技", "603786": "科博达", "600064": "南京高科", "000411": "英特集团", "002372": "伟星新材", "002304": "洋河股份", "601100": "恒立液压", "002460": "赣锋锂业", "002468": "申通快递", "002678": "珠江钢琴", "600787": "中储股份", "000830": "鲁西化工", "603036": "如通股份", "600743": "华远地产", "600203": "福日电子", "003000": "劲仔食品", "600138": "中青旅", "603725": "天安新材", "600982": "宁波能源", "600248": "陕建股份", "603533": "掌阅科技", "001288": "运机集团", "603312": "西典新能", "002233": "塔牌集团", "600120": "浙江东方", "603637": "镇海股份", "002429": "兆驰股份", "003004": "声迅股份", "603005": "晶方科技", "000631": "顺发恒业", "001368": "通达创智", "603299": "苏盐井神", "000501": "武商集团", "002747": "埃斯顿", "600116": "三峡水利", "002239": "奥特佳", "603288": "海天味业", "600269": "赣粤高速", "601689": "拓普集团", "603888": "新华网", "002027": "分众传媒", "603300": "华铁应急", "002077": "大港股份", "000925": "众合科技", "001965": "招商公路", "601326": "秦港股份", "603318": "水发燃气", "002292": "奥飞娱乐", "600461": "洪城环境", "000882": "华联股份", "600363": "联创光电", "002659": "凯文教育", "603344": "星德胜", "000719": "中原传媒", "600973": "宝胜股份", "605177": "东亚药业", "601666": "平煤股份", "002833": "弘亚数控", "002334": "英威腾", "002249": "大洋电机", "601059": "信达证券", "603678": "火炬电子", "603527": "众源新材", "603918": "金桥信息", "002114": "罗平锌电", "605166": "聚合顺", "603269": "海鸥股份", "600838": "XD上海九", "600681": "百川能源", "000758": "中色股份", "603217": "元利科技", "600820": "XD隧道股", "002496": "辉丰股份", "000690": "宝新能源", "002851": "麦格米特", "600141": "兴发集团", "600845": "宝信软件", "001216": "华瓷股份", "000507": "珠海港", "600063": "皖维高新", "603071": "物产环能", "002079": "苏州固锝", "000989": "ST九芝", "002554": "惠博普", "000520": "凤凰航运", "000923": "河钢资源", "603170": "宝立食品", "002454": "松芝股份", "605168": "三人行", "601808": "中海油服", "002501": "利源股份", "603667": "五洲新春", "603137": "恒尚节能", "603012": "创力集团", "600578": "京能电力", "605018": "长华集团", "601500": "通用股份", "002691": "冀凯股份", "603636": "南威软件", "002492": "恒基达鑫", "002539": "云图控股", "002040": "南 京 港", "603075": "热威股份", "000591": "太阳能", "002003": "伟星股份", "605268": "王力安防", "603111": "康尼机电", "601065": "江盐集团", "601512": "中新集团", "603306": "华懋科技", "002614": "奥佳华", "600268": "国电南自", "603960": "克来机电", "601388": "怡球资源", "600221": "海航控股", "002202": "金风科技", "600439": "瑞贝卡", "600128": "苏豪弘业", "002568": "百润股份", "603010": "万盛股份", "601238": "广汽集团", "600629": "华建集团", "000301": "东方盛虹", "600223": "福瑞达", "600096": "云天化", "002358": "森源电气", "600826": "兰生股份", "000655": "金岭矿业", "603919": "金徽酒", "603329": "上海雅仕", "603663": "三祥新材", "000728": "国元证券", "001289": "龙源电力", "601005": "重庆钢铁", "600340": "华夏幸福", "600094": "大名城", "000885": "城发环境", "600238": "海南椰岛", "600780": "通宝能源", "603969": "银龙股份", "002483": "润邦股份", "002132": "恒星科技", "600563": "法拉电子", "002953": "日丰股份", "002673": "西部证券", "603698": "航天工程", "003008": "开普检测", "002722": "物产金轮", "603899": "晨光股份", "002850": "科达利", "000786": "北新建材", "600782": "新钢股份", "001333": "光华股份", "600977": "XD中国电", "601901": "方正证券", "603565": "中谷物流", "600755": "厦门国贸", "603132": "金徽股份", "002465": "海格通信", "600259": "广晟有色", "000850": "华茂股份", "601882": "海天精工", "601677": "明泰铝业", "000782": "恒申新材", "603393": "新天然气", "600726": "华电能源", "600470": "六国化工", "002522": "浙江众成", "000897": "津滨发展", "000419": "通程控股", "605500": "森林包装", "002108": "沧州明珠", "600435": "北方导航", "002820": "桂发祥", "600861": "北京人力", "000607": "华媒控股", "600730": "中国高科", "002774": "快意电梯", "002267": "陕天然气", "600316": "洪都航空", "002342": "巨力索具", "002677": "浙江美大", "600768": "宁波富邦", "002105": "信隆健康", "002723": "小崧股份", "002537": "海联金汇", "002741": "光华科技", "600824": "XD益民集", "600421": "华嵘控股", "000829": "天音控股", "603528": "多伦科技", "601002": "晋亿实业", "600744": "华银电力", "002200": "ST交投", "601696": "中银证券", "600927": "永安期货", "600032": "浙江新能", "002123": "梦网科技", "603706": "东方环宇", "601579": "会稽山", "600230": "沧州大化", "603758": "秦安股份", "600860": "京城股份", "603059": "倍加洁", "600066": "宇通客车", "002686": "亿利达", "000917": "电广传媒", "001209": "洪兴股份", "001234": "泰慕士", "603192": "汇得科技", "002103": "广博股份", "000004": "国华网安", "601949": "中国出版", "601568": "北元集团", "000955": "欣龙控股", "002860": "星帅尔", "002518": "科士达", "600137": "浪莎股份", "000504": "南华生物", "002350": "北京科锐", "600234": "*ST科新", "600206": "有研新材", "000568": "泸州老窖", "601330": "绿色动力", "002112": "三变科技", "002227": "奥 特 迅", "600061": "国投资本", "002326": "永太科技", "601236": "红塔证券", "000534": "万泽股份", "600239": "云南城投", "605133": "嵘泰股份", "002790": "瑞尔特", "002878": "元隆雅图", "603759": "海天股份", "000601": "韶能股份", "600596": "新安股份", "002434": "万里扬", "000905": "厦门港务", "000428": "华天酒店", "601816": "京沪高铁", "600854": "春兰股份", "600825": "新华传媒", "000633": "合金投资", "603050": "科林电气", "601038": "一拖股份", "002386": "天原股份", "600933": "爱柯迪", "603339": "四方科技", "000430": "张家界", "002788": "鹭燕医药", "600369": "西南证券", "601519": "大智慧", "002497": "雅化集团", "603836": "海程邦达", "002120": "韵达股份", "600109": "国金证券", "000709": "河钢股份", "600758": "辽宁能源", "002223": "鱼跃医疗", "600802": "福建水泥", "002110": "三钢闽光", "000691": "亚太实业", "000530": "冰山冷热", "002446": "盛路通信", "002672": "东江环保", "000812": "陕西金叶", "002507": "涪陵榨菜", "603086": "先达股份", "600169": "太原重工", "600067": "冠城大通", "002631": "德尔未来", "002238": "天威视讯", "002593": "日上集团", "603233": "大参林", "600368": "五洲交通", "002863": "今飞凯达", "603388": "ST元成", "002717": "岭南股份", "002911": "佛燃能源", "002646": "天佑德酒", "605056": "咸亨国际", "603020": "爱普股份", "605337": "李子园", "601615": "明阳智能", "600795": "国电电力", "600323": "瀚蓝环境", "600395": "盘江股份", "600518": "康美药业", "002073": "软控股份", "001217": "华尔泰", "000525": "ST红太阳", "002293": "罗莱生活", "600798": "宁波海运", "600688": "上海石化", "603101": "汇嘉时代", "600909": "华安证券", "600717": "天津港", "600556": "天下秀", "603877": "太平鸟", "603385": "惠达卫浴", "600917": "重庆燃气", "600570": "恒生电子", "600848": "上海临港", "600583": "海油工程", "000959": "首钢股份", "600284": "浦东建设", "002129": "TCL中环", "000887": "中鼎股份", "002561": "徐家汇", "002067": "景兴纸业", "600571": "信雅达", "001226": "拓山重工", "002479": "富春环保", "002469": "三维化学", "600929": "雪天盐业", "603237": "五芳斋", "600993": "马应龙", "603958": "哈森股份", "000088": "盐 田 港", "000561": "烽火电子", "600956": "新天绿能", "600655": "豫园股份", "000903": "云内动力", "605060": "联德股份", "600312": "平高电气", "600021": "上海电力", "002998": "优彩资源", "002466": "天齐锂业", "002127": "南极电商", "605208": "永茂泰", "603227": "雪峰科技", "600189": "泉阳泉", "603948": "建业股份", "000407": "胜利股份", "600265": "景谷林业", "000539": "粤电力Ａ", "002707": "众信旅游", "600126": "杭钢股份", "002245": "蔚蓝锂芯", "002360": "同德化工", "002613": "北玻股份", "000895": "双汇发展", "600885": "宏发股份", "600398": "海澜之家", "600805": "悦达投资", "000860": "顺鑫农业", "002786": "银宝山新", "601996": "丰林集团", "002623": "亚玛顿", "000912": "泸天化", "000066": "中国长城", "600212": "绿能慧充", "001228": "永泰运", "000921": "海信家电", "002795": "永和智控", "603626": "科森科技", "600581": "八一钢铁", "601010": "文峰股份", "603800": "道森股份", "600184": "光电股份", "002536": "飞龙股份", "000055": "方大集团", "000505": "京粮控股", "000503": "国新健康", "002808": "ST恒久", "002692": "远程股份", "002092": "ST中泰", "000967": "盈峰环境", "002578": "闽发铝业", "600712": "南宁百货", "000012": "南  玻Ａ", "600737": "中粮糖业", "600742": "一汽富维", "600506": "统一股份", "002549": "凯美特气", "002063": "远光软件", "000010": "美丽生态", "600258": "首旅酒店", "000677": "恒天海龙", "600079": "人福医药", "603586": "金麒麟", "603713": "密尔克卫", "002368": "太极股份", "603045": "福达合金", "600057": "厦门象屿", "601139": "深圳燃气", "601858": "中国科传", "600814": "杭州解百", "000417": "合百集团", "600419": "天润乳业", "600127": "金健米业", "600436": "片仔癀", "600816": "建元信托", "603077": "和邦生物", "600546": "山煤国际", "603076": "乐惠国际", "603040": "新坐标", "603268": "松发股份", "605011": "杭州热电", "002487": "大金重工", "002543": "万和电气", "603995": "甬金股份", "600218": "全柴动力", "600874": "创业环保", "002732": "燕塘乳业", "601718": "际华集团", "600403": "大有能源", "003023": "彩虹集团", "002734": "利民股份", "603697": "有友食品", "002638": "勤上股份", "002069": "獐子岛", "603093": "南华期货", "003017": "大洋生物", "002163": "海南发展", "002159": "三特索道", "600185": "格力地产", "605222": "起帆电缆", "002670": "国盛金控", "600073": "光明肉业", "603755": "日辰股份", "002500": "山西证券", "600486": "扬农化工", "605339": "南侨食品", "000685": "中山公用", "603273": "天元智能", "000970": "中科三环", "600210": "紫江企业", "600027": "华电国际", "600372": "中航机载", "002563": "森马服饰", "000813": "德展健康", "603486": "科沃斯", "600186": "莲花控股", "002801": "微光股份", "603213": "镇洋发展", "600300": "维维股份", "600100": "同方股份", "603000": "人民网", "601083": "锦江航运", "000733": "振华科技", "603828": "ST柯利达", "002493": "荣盛石化", "605167": "利柏特", "605178": "时空科技", "603335": "迪生力", "002787": "华源控股", "603717": "天域生态", "002054": "德美化工", "603195": "公牛集团", "601228": "广州港", "600792": "云煤能源", "001213": "中铁特货", "001203": "大中矿业", "603212": "赛伍技术", "000551": "创元科技", "600875": "东方电气", "603408": "建霖家居", "600158": "中体产业", "600538": "国发股份", "601222": "林洋能源", "600121": "郑州煤电", "002601": "龙佰集团", "002076": "星光股份", "002046": "国机精工", "002853": "皮阿诺", "002989": "中天精装", "000078": "海王生物", "603583": "捷昌驱动", "002498": "汉缆股份", "002344": "海宁皮城", "002205": "国统股份", "600711": "ST盛屯", "603197": "保隆科技", "600371": "万向德农", "002606": "大连电瓷", "002154": "报 喜 鸟", "000767": "晋控电力", "000584": "*ST工智", "002126": "银轮股份", "603177": "德创环保", "603038": "华立股份", "603680": "今创集团", "000652": "泰达股份", "600278": "东方创业", "600822": "上海物贸", "600658": "电子城", "600330": "天通股份", "000799": "酒鬼酒", "603876": "鼎胜新材", "002661": "克明食品", "600429": "三元股份", "000796": "ST凯撒", "600315": "XD上海家", "003042": "中农联合", "001266": "宏英智能", "002392": "北京利尔", "002641": "公元股份", "600663": "陆家嘴", "601096": "宏盛华源", "002526": "山东矿机", "601198": "东兴证券", "002031": "巨轮智能", "600039": "四川路桥", "002074": "国轩高科", "000968": "蓝焰控股", "000612": "焦作万方", "002083": "孚日股份", "603681": "永冠新材", "002545": "东方铁塔", "002330": "得利斯", "601881": "中国银河", "600769": "祥龙电业", "603013": "亚普股份", "600560": "金自天正", "002930": "宏川智慧", "600075": "新疆天业", "600012": "皖通高速", "000993": "闽东电力", "603617": "君禾股份", "600480": "凌云股份", "601702": "华峰铝业", "002939": "长城证券", "001258": "立新能源", "000025": "特  力Ａ", "002153": "石基信息", "600052": "东望时代", "605266": "健之佳", "000404": "长虹华意", "001331": "胜通能源", "603768": "常青股份", "003041": "真爱美家", "603657": "春光科技", "002996": "顺博合金", "601619": "嘉泽新能", "600724": "宁波富达", "002208": "合肥城建", "601727": "上海电气", "000620": "新华联", "600011": "华能国际", "002639": "雪人股份", "000559": "万向钱潮", "601216": "君正集团", "002019": "亿帆医药", "601000": "唐山港", "603618": "杭电股份", "603041": "美思德", "605050": "福然德", "600597": "光明乳业", "601016": "节能风电", "603885": "吉祥航空", "002338": "奥普光电", "600199": "金种子酒", "600516": "方大炭素", "000657": "中钨高新", "600851": "海欣股份", "600618": "氯碱化工", "002210": "飞马国际", "002061": "浙江交科", "001222": "源飞宠物", "600918": "中泰证券", "000510": "新金路", "600935": "华塑股份", "002215": "诺 普 信", "000886": "海南高速", "603776": "永安行", "002423": "中粮资本", "600070": "*ST富润", "603658": "安图生物", "002598": "山东章鼓", "000155": "川能动力", "600588": "用友网络", "600179": "安通控股", "002296": "辉煌科技", "000563": "陕国投Ａ", "603683": "晶华新材", "600740": "山西焦化", "001330": "博纳影业", "600628": "XD新世界", "600351": "亚宝药业", "002569": "ST步森", "002044": "美年健康", "000598": "兴蓉环境", "603182": "嘉华股份", "002858": "力盛体育", "002783": "凯龙股份", "600626": "申达股份", "002216": "三全食品", "001286": "陕西能源", "603116": "红蜻蜓", "600118": "中国卫星", "600299": "安迪苏", "000930": "中粮科技", "603711": "香飘飘", "603270": "金帝股份", "600567": "山鹰国际", "002131": "利欧股份", "600714": "金瑞矿业", "000638": "万方发展", "600367": "红星发展", "603949": "雪龙集团", "002167": "东方锆业", "603823": "百合花", "001324": "长青科技", "601375": "中原证券", "600287": "ST舜天", "002969": "嘉美包装", "000862": "银星能源", "000524": "岭南控股", "600736": "苏州高新", "002726": "龙大美食", "603456": "九洲药业", "600774": "汉商集团", "000898": "鞍钢股份", "601126": "四方股份", "600527": "江南高纤", "000802": "北京文化", "603501": "韦尔股份", "600710": "苏美达", "002419": "天虹股份", "603977": "国泰集团", "600502": "安徽建工", "600136": "ST明诚", "002471": "中超控股", "002343": "慈文传媒", "000809": "*ST和展", "000423": "东阿阿胶", "002890": "弘宇股份", "600392": "盛和资源", "600405": "动力源", "603808": "歌力思", "603099": "长白山", "002666": "德联集团", "001255": "博菲电气", "002508": "老板电器", "002769": "普路通", "002951": "*ST金时", "002753": "永东股份", "000151": "中成股份", "600863": "内蒙华电", "002575": "群兴玩具", "000672": "上峰水泥", "002608": "江苏国信", "002946": "新乳业", "001366": "播恩集团", "603109": "神驰机电", "601995": "中金公司", "002286": "保龄宝", "002243": "力合科创", "000825": "太钢不锈", "002367": "康力电梯", "603609": "禾丰股份", "000546": "金圆股份", "002158": "汉钟精机", "000969": "安泰科技", "002758": "浙农股份", "000738": "航发控制", "603530": "神马电力", "600562": "国睿科技", "603181": "皇马科技", "002204": "大连重工", "601678": "滨化股份", "603893": "瑞芯微", "603689": "皖天然气", "601156": "东航物流", "002146": "荣盛发展", "000990": "诚志股份", "002136": "安 纳 达", "600662": "外服控股", "000058": "深 赛 格", "603338": "浙江鼎力", "001332": "锡装股份", "600749": "西藏旅游", "603990": "麦迪科技", "002658": "雪迪龙", "600649": "城投控股", "600858": "银座股份", "002706": "良信股份", "600783": "鲁信创投", "002407": "多氟多", "603308": "应流股份", "601992": "金隅集团", "000837": "秦川机床", "002241": "歌尔股份", "000721": "西安饮食", "002571": "德力股份", "000029": "深深房Ａ", "605287": "德才股份", "002760": "凤形股份", "600327": "大东方", "000567": "海德股份", "605377": "华旺科技", "600512": "腾达建设", "603777": "来伊份", "600623": "华谊集团", "000635": "英 力 特", "002533": "金杯电工", "000777": "中核科技", "002056": "横店东磁", "002945": "华林证券", "601108": "财通证券", "605090": "九丰能源", "000422": "湖北宜化", "600612": "老凤祥", "600168": "武汉控股", "601456": "国联证券", "603332": "苏州龙杰", "002310": "*ST东园", "000965": "天保基建", "000619": "海螺新材", "000610": "西安旅游", "600305": "恒顺醋业", "603191": "望变电气", "000722": "湖南发展", "003013": "地铁设计", "000828": "东莞控股", "600587": "新华医疗", "603105": "芯能科技", "600241": "时代万恒", "000415": "渤海租赁", "600906": "财达证券", "002181": "粤 传 媒", "605179": "一鸣食品", "002333": "罗普斯金", "002328": "新朋股份", "002728": "特一药业", "603115": "海星股份", "002171": "楚江新材", "600149": "廊坊发展", "600458": "时代新材", "000096": "广聚能源", "603816": "顾家家居", "002084": "海鸥住工", "002057": "中钢天源", "002125": "湘潭电化", "600979": "广安爱众", "603679": "华体科技", "605336": "帅丰电器", "600682": "南京新百", "000498": "山东路桥", "002778": "中晟高科", "603183": "建研院", "002842": "翔鹭钨业", "000761": "本钢板材", "000006": "深振业Ａ", "002731": "萃华珠宝", "002010": "传化智联", "600495": "晋西车轴", "002361": "神剑股份", "600359": "新农开发", "600675": "中华企业", "600387": "*ST海越", "000570": "苏常柴Ａ", "002324": "普利特", "002824": "和胜股份", "600397": "安源煤业", "002506": "协鑫集成", "603727": "博迈科", "603055": "台华新材", "603365": "水星家纺", "002582": "好想你", "002397": "梦洁股份", "603179": "新泉股份", "003038": "鑫铂股份", "601890": "亚星锚链", "002081": "金 螳 螂", "000678": "襄阳轴承", "600236": "桂冠电力", "000783": "长江证券", "603511": "爱慕股份", "002883": "中设股份", "002226": "江南化工", "603992": "松霖科技", "002024": "ST易购", "603291": "联合水务", "000035": "中国天楹", "603353": "和顺石油", "601188": "龙江交通", "002960": "青鸟消防", "002254": "泰和新材", "600689": "上海三毛", "603267": "鸿远电子", "002353": "杰瑞股份", "000785": "居然之家", "603316": "诚邦股份", "000002": "万  科Ａ", "002111": "威海广泰", "600761": "安徽合力", "002151": "北斗星通", "002258": "利尔化学", "002170": "芭田股份", "600098": "广州发展", "600493": "凤竹纺织", "002780": "三夫户外", "603321": "梅轮电梯", "600155": "华创云信", "002800": "天顺股份", "002217": "*ST合泰", "002852": "道道全", "600639": "浦东金桥", "000795": "英洛华", "002803": "吉宏股份", "002187": "广百股份", "600683": "京投发展", "002668": "TCL智家", "002224": "三 力 士", "002090": "金智科技", "001299": "美能能源", "600509": "天富能源", "000090": "天健集团", "600496": "精工钢构", "002616": "长青集团", "600715": "*ST文投", "000009": "中国宝安", "603916": "苏博特", "600007": "中国国贸", "600739": "辽宁成大", "600828": "茂业商业", "600624": "复旦复华", "002480": "新筑股份", "002557": "洽洽食品", "002374": "中锐股份", "603577": "汇金通", "600097": "开创国际", "600366": "宁波韵升", "002265": "建设工业", "000966": "长源电力", "000531": "穗恒运Ａ", "601116": "三江购物", "002590": "万安科技", "003022": "联泓新科", "601952": "苏垦农发", "600708": "光明地产", "002949": "华阳国际", "002712": "思美传媒", "002630": "华西能源", "002442": "龙星化工", "002398": "垒知集团", "001202": "炬申股份", "002297": "博云新材", "605028": "世茂能源", "002862": "实丰文化", "600738": "丽尚国潮", "000609": "*ST中迪", "000875": "吉电股份", "000528": "柳    工", "601900": "南方传媒", "605488": "福莱新材", "002759": "天际股份", "002478": "常宝股份", "002206": "海 利 得", "603029": "天鹅股份", "603290": "斯达半导", "600517": "国网英大", "603598": "引力传媒", "002242": "九阳股份", "002671": "龙泉股份", "600617": "国新能源", "600176": "中国巨石", "002253": "川大智胜", "603648": "畅联股份", "000876": "新 希 望", "600872": "中炬高新", "002149": "西部材料", "603026": "石大胜华", "002284": "亚太股份", "002268": "电科网安", "000030": "富奥股份", "600416": "湘电股份", "601106": "中国一重", "000639": "西王食品", "002615": "哈尔斯", "002182": "宝武镁业", "600988": "赤峰黄金", "003030": "祖名股份", "002377": "国创高新", "000686": "东北证券", "002456": "欧菲光", "000548": "湖南投资", "603171": "税友股份", "600595": "中孚实业", "601279": "英利汽车", "001270": "铖昌科技", "002234": "民和股份", "603221": "爱丽家居", "002173": "创新医疗", "600785": "新华百货", "600008": "首创环保", "002383": "合众思壮", "603708": "家家悦", "000565": "渝三峡Ａ", "000059": "华锦股份", "000586": "汇源通信", "002266": "浙富控股", "603666": "亿嘉和", "601798": "蓝科高新", "002176": "江特电机", "600693": "东百集团", "600475": "华光环能", "002427": "尤夫股份", "000839": "中信国安", "000629": "钒钛股份", "600345": "XD长江通", "000899": "赣能股份", "600099": "林海股份", "603819": "神力股份", "600365": "ST通葡", "605009": "豪悦护理", "002828": "贝肯能源", "605169": "洪通燃气", "603178": "圣龙股份", "601599": "浙文影业", "601069": "西部黄金", "000717": "中南股份", "002011": "盾安环境", "605388": "均瑶健康", "600939": "重庆建工", "001337": "四川黄金", "002544": "普天科技", "000599": "青岛双星", "605577": "龙版传媒", "002857": "三晖电气", "603980": "吉华集团", "600705": "中航产融", "002141": "*ST贤丰", "605080": "浙江自然", "002789": "建艺集团", "600528": "中铁工业", "002381": "双箭股份", "000576": "甘化科工", "002088": "鲁阳节能", "002541": "鸿路钢构", "601333": "XD广深铁", "600477": "杭萧钢构", "605123": "派克新材", "000519": "中兵红箭", "002302": "西部建设", "000987": "越秀资本", "603810": "丰山集团", "002591": "恒大高新", "600636": "国新文化", "600208": "新湖中宝", "600157": "永泰能源", "600152": "维科技术", "601827": "三峰环境", "601969": "海南矿业", "002445": "中南文化", "601015": "陕西黑猫", "600651": "飞乐音响", "600586": "金晶科技", "002430": "杭氧股份", "603985": "恒润股份", "600232": "金鹰股份", "002277": "友阿股份", "600877": "电科芯片", "600633": "浙数文化", "600992": "贵绳股份", "002072": "凯瑞德", "002331": "皖通科技", "603569": "长久物流", "600827": "百联股份", "600720": "中交设计", "000603": "盛达资源", "002142": "宁波银行", "603097": "江苏华辰", "002455": "百川股份", "603399": "永杉锂业", "600078": "澄星股份", "002521": "齐峰新材", "603612": "索通发展", "600023": "浙能电力", "603903": "中持股份", "002856": "美芝股份", "000573": "粤宏远Ａ", "000553": "安道麦A", "605286": "同力日升", "002023": "海特高新", "002452": "长高电新", "002214": "大立科技", "600170": "上海建工", "002693": "双成药业", "603345": "安井食品", "000859": "国风新材", "601011": "宝泰隆", "002006": "精工科技", "000958": "电投产融", "601311": "骆驼股份", "000680": "山推股份", "600135": "乐凯胶片", "600217": "中再资环", "603153": "上海建科", "600148": "长春一东", "600916": "中国黄金", "600389": "江山股份", "600173": "卧龙地产", "002714": "牧原股份", "600859": "王府井", "603518": "锦泓集团", "002756": "永兴材料", "605117": "德业股份", "002832": "比音勒芬", "600133": "东湖高新", "002628": "成都路桥", "603861": "白云电器", "603766": "隆鑫通用", "002174": "游族网络", "002893": "京能热力", "002961": "瑞达期货", "000668": "荣丰控股", "000421": "南京公用", "603429": "集友股份", "600500": "中化国际", "600266": "城建发展", "600525": "长园集团", "002336": "*ST人乐", "000779": "甘咨询", "600796": "钱江生化", "603682": "锦和商管", "601200": "上海环境", "600579": "克劳斯", "603110": "东方材料", "600095": "湘财股份", "600961": "株冶集团", "600552": "凯盛科技", "603363": "*ST傲农", "002345": "潮宏基", "000537": "中绿电", "600559": "老白干酒", "600603": "广汇物流", "600415": "小商品城", "600901": "江苏金租", "002586": "*ST围海", "002494": "华斯股份", "002321": "华英农业", "600499": "科达制造", "001338": "永顺泰", "603032": "德新科技", "600207": "安彩高科", "600202": "哈空调", "001896": "豫能控股", "000821": "京山轻机", "002743": "富煌钢构", "600882": "妙可蓝多", "002777": "久远银海", "000801": "四川九洲", "603135": "中重科技", "600862": "中航高科", "603003": "*ST龙宇", "000014": "沙河股份", "600408": "安泰集团", "002066": "瑞泰科技", "601068": "中铝国际", "600589": "广东榕泰", "000061": "农 产 品", "002534": "西子洁能", "601566": "九牧王", "002318": "久立特材", "600881": "亚泰集团", "002035": "华帝股份", "601086": "国芳集团", "600510": "黑牡丹", "002573": "清新环境", "002805": "丰元股份", "600006": "东风股份", "603272": "联翔股份", "002240": "盛新锂能", "600543": "莫高股份", "000605": "渤海股份", "000593": "德龙汇能", "000032": "深桑达Ａ", "002715": "登云股份", "600156": "华升股份", "601608": "中信重工", "002121": "科陆电子", "002511": "中顺洁柔", "603516": "淳中科技", "600235": "民丰特纸", "002305": "南国置业", "002247": "聚力文化", "003035": "南网能源", "603693": "江苏新能", "600883": "博闻科技", "002191": "劲嘉股份", "002373": "千方科技", "600059": "古越龙山", "002868": "绿康生化", "600800": "渤海化学", "002188": "中天服务", "000922": "佳电股份", "603825": "华扬联众", "001316": "润贝航科", "600391": "航发科技", "600894": "广日股份", "600965": "福成股份", "000708": "中信特钢", "002385": "大北农", "001236": "弘业期货", "603938": "三孚股份", "600831": "ST广网", "600540": "新赛股份", "002838": "道恩股份", "000797": "中国武夷", "002719": "麦趣尔", "603330": "天洋新材", "600358": "国旅联合", "603787": "新日股份", "600679": "上海凤凰", "603709": "中源家居", "002062": "宏润建设", "603730": "岱美股份", "600467": "好当家", "600702": "舍得酒业", "002033": "丽江股份", "603315": "福鞍股份", "600879": "航天电子", "002570": "贝因美", "002558": "巨人网络", "603863": "松炀资源", "600125": "铁龙物流", "000069": "华侨城Ａ", "002718": "友邦吊顶", "000516": "国际医学", "600505": "西昌电力", "600448": "华纺股份", "002276": "万马股份", "600706": "曲江文旅", "000089": "深圳机场", "002135": "东南网架", "000929": "兰州黄河", "000338": "潍柴动力", "603733": "仙鹤股份", "002140": "东华科技", "000927": "中国铁物", "002560": "通达股份", "002514": "宝馨科技", "601033": "永兴股份", "603377": "ST东时", "002513": "蓝丰生化", "600621": "华鑫股份", "002183": "怡 亚 通", "000759": "中百集团", "603909": "建发合诚", "002867": "周大生", "603218": "日月股份", "600808": "马钢股份", "600293": "三峡新材", "002225": "濮耐股份", "002145": "中核钛白", "000036": "华联控股", "600876": "凯盛新能", "600295": "鄂尔多斯", "003039": "顺控发展", "600844": "丹化科技", "002264": "新 华 都", "002179": "中航光电", "002439": "启明星辰", "002887": "绿茵生态", "603007": "ST花王", "000803": "山高环能", "002918": "蒙娜丽莎", "002709": "天赐材料", "002933": "新兴装备", "603057": "紫燕食品", "601368": "绿城水务", "002218": "拓日新能", "002229": "鸿博股份", "002910": "庄园牧场", "001914": "招商积余", "002651": "利君股份", "600599": "ST熊猫", "002190": "成飞集成", "001313": "粤海饲料", "000791": "甘肃能源", "605180": "华生科技", "600619": "海立股份", "603739": "蔚蓝生物", "601369": "陕鼓动力", "002806": "华锋股份", "600641": "万业企业", "603208": "江山欧派", "600320": "振华重工", "600072": "中船科技", "600733": "北汽蓝谷", "002414": "高德红外", "600970": "中材国际", "000663": "永安林业", "002999": "天禾股份", "600038": "中直股份", "603838": "四通股份", "002669": "康达新材", "605089": "味知香", "002259": "ST升达", "000037": "深南电A", "001872": "招商港口", "603726": "朗迪集团", "002357": "富临运业", "002175": "东方智造", "002097": "山河智能", "605196": "华通线缆", "603950": "长源东谷", "000723": "美锦能源", "600779": "水井坊", "002068": "黑猫股份", "002166": "莱茵生物", "002645": "华宏科技", "603030": "全筑股份", "600545": "卓郎智能", "600580": "卧龙电驱", "601136": "首创证券", "603285": "键邦股份", "002375": "亚厦股份", "603737": "三棵树", "603100": "川仪股份", "002354": "天娱数科", "600195": "中牧股份", "601179": "中国西电", "002157": "正邦科技", "600615": "丰华股份", "002295": "精艺股份", "603279": "景津装备", "603063": "禾望电气", "600468": "百利电气", "600893": "航发动力", "003027": "同兴环保", "002624": "完美世界", "600857": "宁波中百", "600335": "国机汽车", "603176": "汇通集团", "603131": "上海沪工", "601869": "XD长飞光", "000017": "深中华A", "600547": "山东黄金", "000560": "我爱我家", "600864": "哈投股份", "600884": "杉杉股份", "002928": "华夏航空", "002523": "天桥起重", "603326": "我乐家居", "600880": "博瑞传播", "002015": "协鑫能科", "603833": "欧派家居", "002875": "安奈儿", "000401": "冀东水泥", "603136": "天目湖", "603226": "菲林格尔", "000600": "建投能源", "600960": "渤海汽车", "001322": "箭牌家居", "603813": "原尚股份", "601117": "中国化学", "000811": "冰轮环境", "002327": "富安娜", "003033": "征和工业", "000735": "罗 牛 山", "600727": "鲁北化工", "600302": "标准股份", "002643": "万润股份", "002193": "如意集团", "002356": "赫美集团", "000951": "中国重汽", "002992": "宝明科技", "600692": "亚通股份", "600281": "华阳新材", "002250": "联化科技", "600643": "爱建集团", "603815": "交建股份", "002572": "索菲亚", "002100": "天康生物", "600835": "上海机电", "600110": "诺德股份", "603155": "新亚强", "600644": "乐山电力", "600489": "中金黄金", "002700": "ST浩源", "603069": "海汽集团", "600187": "国中水务", "600725": "云维股份", "600653": "申华控股", "002696": "百洋股份", "001376": "百通能源", "603505": "金石资源", "000420": "吉林化纤", "600846": "同济科技", "600478": "XD科力远", "000056": "皇庭国际", "003012": "东鹏控股", "603712": "七一二", "600399": "抚顺特钢", "002625": "光启技术", "600354": "敦煌种业", "002611": "东方精工", "002060": "广东建工", "000543": "皖能电力", "600159": "大龙地产", "000545": "金浦钛业", "002973": "侨银股份", "002306": "中科云网", "601636": "旗滨集团", "600491": "龙元建设", "603937": "丽岛新材", "600386": "北巴传媒", "600990": "四创电子", "002812": "恩捷股份", "603126": "中材节能", "002548": "金新农", "002133": "广宇集团", "002116": "中国海诚", "000856": "冀东装备", "601208": "东材科技", "603017": "中衡设计", "603317": "天味食品", "002109": "兴化股份", "000718": "苏宁环球", "002484": "江海股份", "603008": "喜临门", "600361": "创新新材", "000883": "湖北能源", "002428": "云南锗业", "600748": "上实发展", "603566": "普莱柯", "600674": "川投能源", "002555": "三七互娱", "600741": "华域汽车", "002270": "华明装备", "002679": "福建金森", "002927": "泰永长征", "603506": "南都物业", "000736": "中交地产", "600355": "精伦电子", "603128": "华贸物流", "002237": "恒邦股份", "002682": "龙洲股份", "603489": "八方股份", "600526": "菲达环保", "603391": "力聚热能", "603797": "联泰环保", "002278": "神开股份", "600657": "信达地产", "002443": "金洲管道", "000697": "炼石航空", "600537": "亿晶光电", "601698": "中国卫通", "000572": "海马汽车", "002574": "明牌珠宝", "600819": "耀皮玻璃", "600319": "亚星化学", "600166": "福田汽车", "000935": "四川双马", "000715": "中兴商业", "605198": "安德利", "002312": "川发龙蟒", "002746": "仙坛股份", "601828": "美凯龙", "002735": "王子新材", "000488": "晨鸣纸业", "600082": "海泰发展", "603123": "翠微股份", "600630": "龙头股份", "603688": "石英股份", "001300": "三柏硕", "000720": "新能泰山", "603305": "旭升集团", "600760": "中航沈飞", "603278": "大业股份", "601012": "隆基绿能", "603337": "杰克股份", "600325": "华发股份", "600343": "航天动力", "002871": "伟隆股份", "600590": "泰豪科技", "603596": "伯特利", "002075": "沙钢股份", "600151": "航天机电", "002792": "通宇通讯", "000998": "隆平高科", "002931": "锋龙股份", "002039": "黔源电力", "600396": "华电辽能", "002165": "红 宝 丽", "000892": "欢瑞世纪", "603381": "永臻股份", "603966": "法兰泰克", "600058": "五矿发展", "002481": "双塔食品", "000595": "宝塔实业", "002909": "集泰股份", "001326": "联域股份", "000852": "石化机械", "000068": "华控赛格", "603790": "雅运股份", "600227": "赤天化", "603529": "爱玛科技", "600456": "宝钛股份", "603789": "星光农机", "603350": "安乃达", "000981": "山子高科", "002531": "天顺风能", "605006": "山东玻纤", "603113": "金能科技", "603062": "麦加芯彩", "001215": "千味央厨", "600665": "天地源", "000597": "东北制药", "600765": "中航重机", "000798": "中水渔业", "002177": "御银股份", "600481": "双良节能", "603058": "永吉股份", "603988": "中电电机", "603588": "高能环境", "002291": "遥望科技", "603180": "金牌家居", "605288": "凯迪股份", "600313": "农发种业", "002702": "海欣食品", "002685": "华东重机", "002041": "登海种业", "605020": "永和股份", "600622": "光大嘉宝", "002180": "纳思达", "603939": "益丰药房", "600791": "京能置业", "605069": "正和生态", "603843": "正平股份", "001223": "欧克科技", "000928": "中钢国际", "603103": "横店影视", "000670": "盈方微", "600262": "北方股份", "000913": "钱江摩托", "603866": "桃李面包", "600610": "中毅达", "002458": "益生股份", "002459": "晶澳科技", "000816": "智慧农业", "000518": "四环生物", "002413": "雷科防务", "002196": "方正电机", "600638": "新黄浦", "603599": "广信股份", "601929": "吉视传媒", "605358": "立昂微", "600076": "康欣新材", "600855": "航天长峰", "600201": "生物股份", "600310": "广西能源", "002051": "中工国际", "000627": "天茂集团", "603906": "龙蟠科技", "002389": "航天彩虹", "603989": "艾华集团", "002813": "路畅科技", "000007": "全新好", "002517": "恺英网络", "600483": "福能股份", "000016": "深康佳Ａ", "603536": "惠发食品", "603028": "赛福天", "002047": "宝鹰股份", "603033": "三维股份", "002664": "信质集团", "002985": "北摩高科", "001201": "东瑞股份", "000789": "万年青", "600818": "中路股份", "000031": "大悦城", "003037": "三和管桩", "002694": "顾地科技", "600539": "狮头股份", "603117": "万林物流", "600336": "澳柯玛", "002739": "万达电影", "002299": "圣农发展", "600719": "大连热电", "002096": "易普力", "000877": "天山股份", "002585": "双星新材", "002941": "新疆交建", "603580": "艾艾精工", "600318": "新力金融", "603001": "奥康国际", "002085": "万丰奥威", "600770": "综艺股份", "600620": "天宸股份", "000975": "山金国际", "600106": "重庆路桥", "603396": "金辰股份", "601226": "华电重工", "001336": "楚环科技", "603162": "海通发展", "002410": "广联达", "002335": "科华数据", "600984": "建设机械", "002269": "美邦服饰", "000716": "黑芝麻", "000701": "厦门信达", "603887": "城地香江", "600409": "三友化工", "002577": "雷柏科技", "600732": "爱旭股份", "002798": "帝欧家居", "002329": "皇氏集团", "002865": "钧达股份", "600604": "市北高新", "600283": "DR钱江水", "002355": "兴民智通", "603883": "老百姓", "600966": "博汇纸业", "002201": "正威新材", "605305": "中际联合", "002816": "*ST和科", "603616": "韩建河山", "002453": "华软科技", "002535": "林州重机", "002965": "祥鑫科技", "603383": "顶点软件", "001358": "兴欣新材", "002482": "广田集团", "002021": "中捷资源", "002982": "湘佳股份", "603687": "大胜达", "603119": "浙江荣泰", "002605": "姚记科技", "600490": "鹏欣资源", "002695": "煌上煌", "603628": "清源股份", "603188": "亚邦股份", "000838": "财信发展", "600438": "通威股份", "000040": "ST旭蓝", "600696": "岩石股份", "603282": "亚光股份", "002211": "宏达新材", "002059": "云南旅游", "600444": "国机通用", "603778": "国晟科技", "601865": "福莱特", "600257": "大湖股份", "605108": "同庆楼", "002750": "*ST龙津", "603185": "弘元绿能", "003002": "壶化股份", "600691": "阳煤化工", "600107": "美尔雅", "002486": "嘉麟杰", "002495": "佳隆股份", "000042": "中洲控股", "002219": "新里程", "002640": "跨境通", "000608": "阳光股份", "000713": "丰乐种业", "603659": "璞泰来", "000514": "渝 开 发", "002761": "浙江建投", "002490": "ST墨龙", "600132": "重庆啤酒", "603098": "森特股份", "600381": "ST春天", "002576": "通达动力", "002968": "新大正", "600501": "航天晨光", "601155": "新城控股", "601908": "京运通", "000632": "三木集团", "000065": "北方国际", "002425": "凯撒文化", "603806": "福斯特", "603729": "龙韵股份", "600550": "保变电气", "600969": "郴电国际", "603333": "尚纬股份", "002307": "北新路桥", "601606": "长城军工", "600671": "ST目药", "000558": "莱茵体育", "601886": "江河集团", "600231": "凌钢股份", "002596": "海南瑞泽", "001360": "南矿集团", "603721": "中广天择", "001269": "欧晶科技", "002348": "高乐股份", "603173": "福斯达", "600729": "重庆百货", "605303": "园林股份", "002246": "北化股份", "600684": "珠江股份", "603043": "广州酒家", "002476": "宝莫股份", "002043": "兔 宝 宝", "600841": "动力新科", "603955": "大千生态", "603898": "好莱客", "000402": "金 融 街", "600678": "四川金顶", "603168": "莎普爱思", "002791": "坚朗五金", "002775": "文科股份", "000972": "中基健康", "001317": "三羊马", "002212": "天融信", "605188": "国光连锁", "600250": "南京商旅", "001212": "中旗新材", "002607": "中公教育", "600561": "江西长运", "002339": "积成电子", "002766": "索菱股份", "600053": "九鼎投资", "001239": "永达股份", "002431": "棕榈股份", "603719": "良品铺子", "000661": "长春高新", "603090": "宏盛股份", "603366": "日出东方", "000099": "中信海直", "603078": "江化微", "000011": "深物业A", "605111": "新洁能", "000953": "河化股份", "600117": "西宁特钢", "600963": "岳阳林纸", "600773": "西藏城投", "603818": "曲美家居", "603389": "亚振家居", "600593": "大连圣亚", "002915": "中欣氟材", "601595": "上海电影", "000529": "广弘控股", "603801": "志邦家居", "603359": "东珠生态", "002314": "南山控股", "603499": "翔港科技", "002749": "国光股份", "600383": "金地集团", "600449": "宁夏建材", "600337": "美克家居", "000400": "许继电气", "600370": "三房巷", "001230": "劲旅环境", "603021": "山东华鹏", "002124": "ST天邦", "002567": "唐人神", "603869": "ST智知", "600460": "士兰微", "002620": "瑞和股份", "002859": "洁美科技", "003026": "中晶科技", "002963": "豪尔赛", "000757": "浩物股份", "002905": "金逸影视", "600697": "欧亚集团", "603303": "得邦照明", "002647": "仁东控股", "605299": "舒华体育", "600101": "明星电力", "002080": "中材科技", "002308": "*ST威创", "603051": "鹿山新材", "600225": "卓朗科技", "600635": "大众公用", "600609": "金杯汽车", "603357": "设计总院", "600376": "首开股份", "000669": "ST金鸿", "000768": "中航西飞", "000957": "中通客车", "603375": "盛景微", "002418": "康盛股份", "603477": "巨星农牧", "603151": "邦基科技", "600611": "大众交通", "600676": "交运股份", "002271": "东方雨虹", "603444": "吉比特", "002542": "中化岩土", "603515": "欧普照明", "603686": "福龙马", "600975": "新五丰", "600083": "*ST博信", "000793": "华闻集团", "601933": "永辉超市", "605007": "五洲特纸", "002822": "ST中装", "603839": "安正时尚", "002729": "好利科技", "000863": "三湘印象", "000550": "江铃汽车", "001696": "宗申动力", "600192": "长城电工", "603900": "莱绅通灵", "002667": "威领股份", "000712": "锦龙股份", "601515": "东峰集团", "002656": "ST摩登", "603390": "通达电气", "001210": "金房能源", "600650": "锦江在线", "002713": "东易日盛", "603129": "春风动力", "000949": "新乡化纤", "000826": "启迪环境", "000868": "安凯客车", "001379": "腾达科技", "600889": "南京化纤", "002634": "棒杰股份", "002629": "仁智股份", "002565": "顺灏股份", "002829": "星网宇达", "002285": "世联行", "002840": "华统股份", "000901": "航天科技", "002597": "金禾实业", "600280": "中央商场", "605296": "神农集团", "002919": "名臣健康", "603378": "亚士创能", "002207": "准油股份", "603310": "C巍华", "600171": "上海贝岭", "000995": "皇台酒业", "002861": "瀛通通讯", "000890": "法尔胜", "603018": "华设集团", "601028": "玉龙股份", "002405": "四维图新", "600834": "申通地铁", "002827": "高争民爆", "603187": "海容冷链", "000702": "正虹科技", "600163": "中闽能源", "603978": "深圳新星", "000679": "大连友谊", "600452": "涪陵电力", "000509": "华塑控股", "002488": "金固股份", "603458": "勘设股份", "002869": "金溢科技", "002232": "启明信息", "000880": "潍柴重机", "600686": "金龙汽车", "603517": "绝味食品", "605081": "太和水"}